seagulls/app/__init__.py
seagulls/app/_app_interfaces.py
seagulls/app/_plugin_client.py
seagulls/app/_plugin_exceptions.py
seagulls/app/_plugin_interfaces.py
seagulls/app/py.typed
seagulls/assets/__init__.py
seagulls/assets/_manager.py
seagulls/assets/py.typed
seagulls/cli/__init__.py
seagulls/cli/_request.py
seagulls/cli/py.typed
seagulls/debug/__init__.py
seagulls/debug/_debug_hud.py
seagulls/debug/py.typed
seagulls/engine/__init__.py
seagulls/engine/_active_scene_client.py
seagulls/engine/_basic_scene_manager.py
seagulls/engine/_blocking_game_session.py
seagulls/engine/_collisions.py
seagulls/engine/_empty_scene.py
seagulls/engine/_game_clock.py
seagulls/engine/_game_controls.py
seagulls/engine/_game_object.py
seagulls/engine/_game_scene.py
seagulls/engine/_game_scene_manager.py
seagulls/engine/_game_session.py
seagulls/engine/_game_session_manager.py
seagulls/engine/_game_settings.py
seagulls/engine/_pygame.py
seagulls/engine/_surface_renderer.py
seagulls/engine/_window_scene.py
seagulls/engine/py.typed
seagulls/eventing/__init__.py
seagulls/eventing/_interfaces.py
seagulls/eventing/py.typed
seagulls/foo/py.typed
seagulls/rendering/__init__.py
seagulls/rendering/py.typed
seagulls_engine-0.1.0rc1.dist-info/entry_points.txt
seagulls_engine-0.1.0rc1.dist-info/WHEEL
seagulls_engine-0.1.0rc1.dist-info/METADATA
seagulls_engine-0.1.0rc1.dist-info/RECORD
