Metadata-Version: 2.1
Name: seagulls-engine
Version: 0.1.0rc1
Summary: 
License: MIT
Author: Lorenzo Pisani
Author-email: zeelot3k@gmail.com
Requires-Python: >=3.8,<4.0
Classifier: License :: OSI Approved :: MIT License
Classifier: Programming Language :: Python :: 3
Classifier: Programming Language :: Python :: 3.10
Classifier: Programming Language :: Python :: 3.8
Classifier: Programming Language :: Python :: 3.9
Provides-Extra: cli
Provides-Extra: dev
Requires-Dist: PyYAML
Requires-Dist: colorlog; extra == "dev"
Requires-Dist: importlib-metadata
Requires-Dist: pygame
Requires-Dist: seagulls-cli; extra == "cli" or extra == "dev"
Requires-Dist: seagulls-devtools; extra == "dev"
Requires-Dist: types-PyYAML; extra == "dev"
